wint/__init__.py
wint/container.py
wint/decorators.py
wint/descriptor.py
wint/punq/LICENSE
wint/punq/LICENSE
wint/punq/README.md
wint/punq/README.md
wint/punq/__init__.py
wint/punq/__init__.py
wint-0.2.0.dist-info/LICENSE
wint-0.2.0.dist-info/WHEEL
wint-0.2.0.dist-info/METADATA
wint-0.2.0.dist-info/RECORD
