Metadata-Version: 2.1
Name: wint
Version: 0.2.0
Summary: Dependency injection with type hints
Home-page: https://github.com/asyncee/wint
License: MIT
Keywords: dependency injection,type hinting,wint
Author: Stanislav Lobanov
Author-email: n10101010@gmail.com
Requires-Python: >=3.6
Classifier: License :: OSI Approved :: MIT License
Classifier: Programming Language :: Python :: 3
Classifier: Programming Language :: Python :: 3.6
Classifier: Programming Language :: Python :: 3.7
